adcpasciireader/__init__.py
adcpasciireader/adcpreader.py
adcpasciireader-1.1.3.dist-info/METADATA
adcpasciireader-1.1.3.dist-info/WHEEL
adcpasciireader-1.1.3.dist-info/top_level.txt
adcpasciireader-1.1.3.dist-info/RECORD
