Metadata-Version: 2.4
Name: adcpasciireader
Version: 1.1.3
Summary: Code for reading and plotting adcp data from classic ascii output
Author: AP
Dynamic: author
Dynamic: description
Dynamic: summary
